bigdog/__init__.py
bigdog/quantityu.py
bigdog/temptoolclass_pydocument.py
bigdog/temptoolclass_version.py
bigdog/toolclass_pydocument.py
bigdog/toolclass_version.py
bigdog/valueu.py
bigdog-0.2510.13.dist-info/METADATA
bigdog-0.2510.13.dist-info/WHEEL
bigdog-0.2510.13.dist-info/entry_points.txt
bigdog-0.2510.13.dist-info/top_level.txt
bigdog-0.2510.13.dist-info/RECORD
