Metadata-Version: 2.2
Name: bigdog
Version: 0.2510.13
Summary: Test field for pre-release package evaluation
Home-page: https://kohdh.com/
Author: Donghyeok Koh
Author-email: donghyeok.koh.code@gmail.com
Classifier: Development Status :: 3 - Alpha
Classifier: Programming Language :: Python :: 3
Classifier: License :: Other/Proprietary License
Classifier: Operating System :: OS Independent
Classifier: Intended Audience :: Science/Research
Classifier: Topic :: Scientific/Engineering
Requires-Python: >=3.6
Requires-Dist: numpy>=1.23.2
Requires-Dist: scipy>=1.9.2
Requires-Dist: astropy
Dynamic: author
Dynamic: author-email
Dynamic: classifier
Dynamic: description
Dynamic: description-content-type
Dynamic: home-page
Dynamic: requires-dist
Dynamic: requires-python
Dynamic: summary
